ezesri/__init__.py
ezesri/cli.py
ezesri/extract.py
ezesri/utils.py
ezesri-0.3.2.dist-info/licenses/LICENSE
ezesri-0.3.2.dist-info/METADATA
ezesri-0.3.2.dist-info/WHEEL
ezesri-0.3.2.dist-info/entry_points.txt
ezesri-0.3.2.dist-info/top_level.txt
ezesri-0.3.2.dist-info/RECORD
