Metadata-Version: 2.4
Name: ezesri
Version: 0.3.2
Summary: A lightweight Python package for extracting data from Esri REST API endpoints.
Home-page: https://github.com/stiles/ezesri
Author: Justin Myles
Author-email: justin@myles.com
Keywords: esri,gis,geospatial,arcgis,rest-api
Classifier: Programming Language :: Python :: 3
Classifier: License :: OSI Approved :: MIT License
Classifier: Operating System :: OS Independent
Requires-Python: >=3.6
License-File: LICENSE
Requires-Dist: requests
Requires-Dist: geopandas
Requires-Dist: pandas
Requires-Dist: click
Requires-Dist: tqdm
Requires-Dist: fiona
Provides-Extra: docs
Requires-Dist: mkdocs; extra == "docs"
Requires-Dist: mkdocs-material; extra == "docs"
Dynamic: author
Dynamic: author-email
Dynamic: classifier
Dynamic: description
Dynamic: description-content-type
Dynamic: home-page
Dynamic: keywords
Dynamic: license-file
Dynamic: provides-extra
Dynamic: requires-dist
Dynamic: requires-python
Dynamic: summary
